[
    {
        "_id": "7282",
        "nome": "Radiation protection practitioner",
        "disciplinas": [
            "752456",
            "845285",
            "46164",
            "189486",
            "455338",
            "497352",
            "67445"
        ]
    },
    {
        "_id": "49848",
        "nome": "Marketing executive",
        "disciplinas": [
            "431163",
            "13758",
            "513",
            "379144"
        ]
    },
    {
        "_id": "20167",
        "nome": "Engineer, building services",
        "disciplinas": [
            "400100",
            "457880",
            "610484",
            "286678",
            "402383",
            "795235"
        ]
    },
    {
        "_id": "46774",
        "nome": "Engineer, mining",
        "disciplinas": [
            "477128",
            "256215",
            "444121"
        ]
    },
    {
        "_id": "97038",
        "nome": "Communications engineer",
        "disciplinas": [
            "958474",
            "385171",
            "565033",
            "537851",
            "66002"
        ]
    },
    {
        "_id": "79662",
        "nome": "Sub",
        "disciplinas": [
            "577877",
            "68003",
            "659503",
            "657456",
            "539918"
        ]
    },
    {
        "_id": "17024",
        "nome": "Designer, television/film set",
        "disciplinas": [
            "839535",
            "287415",
            "217455",
            "309877"
        ]
    },
    {
        "_id": "80582",
        "nome": "Bookseller",
        "disciplinas": [
            "473091"
        ]
    },
    {
        "_id": "46281",
        "nome": "Ophthalmologist",
        "disciplinas": [
            "309892"
        ]
    },
    {
        "_id": "69433",
        "nome": "Nurse, children's",
        "disciplinas": [
            "916789",
            "921706",
            "663328",
            "420267"
        ]
    }
]